README.rst
setup.cfg
setup.py
SilentDune_Client.egg-info/PKG-INFO
SilentDune_Client.egg-info/SOURCES.txt
SilentDune_Client.egg-info/dependency_links.txt
SilentDune_Client.egg-info/entry_points.txt
SilentDune_Client.egg-info/requires.txt
SilentDune_Client.egg-info/top_level.txt
silentdune_client/__init__.py
silentdune_client/sdc_firewall.py
silentdune_client/sdc_install.py
silentdune_client/builders/__init__.py
silentdune_client/builders/iptables.py
silentdune_client/init/sdc-firewall.systemd.in
silentdune_client/init/sdc-firewall.sysv.in
silentdune_client/init/sdc.conf.systemd.in
silentdune_client/init/sdc.conf.sysv.in
silentdune_client/init/silentdune.logrotate.in
silentdune_client/models/__init__.py
silentdune_client/models/global_preferences.py
silentdune_client/models/iptables_log_event.py
silentdune_client/models/iptables_rules.py
silentdune_client/models/json_base.py
silentdune_client/models/node.py
silentdune_client/models/remote_config.py
silentdune_client/modules/__init__.py
silentdune_client/modules/automation/__init__.py
silentdune_client/modules/automation/auto_discovery/__init__.py
silentdune_client/modules/automation/auto_discovery/base_discovery_service.py
silentdune_client/modules/automation/auto_discovery/dhcp.py
silentdune_client/modules/automation/auto_discovery/dns.py
silentdune_client/modules/automation/auto_discovery/icmp.py
silentdune_client/modules/automation/auto_discovery/ntp.py
silentdune_client/modules/automation/auto_discovery/updates.py
silentdune_client/modules/automation/auto_services/__init__.py
silentdune_client/modules/automation/auto_services/base_service.py
silentdune_client/modules/automation/auto_services/docker.py
silentdune_client/modules/comm/__init__.py
silentdune_client/modules/comm/remote_config/__init__.py
silentdune_client/modules/comm/sd_server/__init__.py
silentdune_client/modules/comm/sd_server/connection.py
silentdune_client/modules/examples/__init__.py
silentdune_client/modules/examples/simple/__init__.py
silentdune_client/modules/firewall/__init__.py
silentdune_client/modules/firewall/logging/__init__.py
silentdune_client/modules/firewall/manager/__init__.py
silentdune_client/modules/firewall/manager/iptables_utils.py
