Metadata-Version: 1.1
Name: SilentDune-Client
Version: 0.5.14
Summary: Silent Dune FPA Client
Home-page: https://github.com/EntPack/SilentDune-Client
Author: Robert Abram
Author-email: robert.abram@entpack.com
License: UNKNOWN
Download-URL: https://github.com/EntPack/SilentDune-Client/tarball/0.1
Keywords: firewall,security
Platform: UNKNOWN
Classifier: Development Status :: 4 - Beta
Classifier: Programming Language :: Python
Classifier: Environment :: Console
Classifier: License :: OSI Approved :: GNU General Public License v3 (GPLv3)
Classifier: Operating System :: POSIX :: Linux
